uhb/__init__.py
uhb/analytical.py
uhb/cli.py
uhb/foundation.py
uhb/general.py
uhb/psi.py
uhb/ramberg.py
uhb-0.0.3.dist-info/METADATA
uhb-0.0.3.dist-info/RECORD
uhb-0.0.3.dist-info/WHEEL
uhb-0.0.3.dist-info/entry_points.txt
uhb-0.0.3.dist-info/top_level.txt
