Metadata-Version: 2.1
Name: uhb
Version: 0.0.3
Summary: UNKNOWN
Home-page: https://github.com/benranderson/uhb
Author: Ben Randerson
Author-email: ben.m.randerson@gmail.com
License: MIT License
Keywords: upheaval buckling uhb engineering pipelines
Platform: UNKNOWN
Classifier: Development Status :: 3 - Alpha
Classifier: Intended Audience :: Other Audience
Classifier: Topic :: Scientific/Engineering
Classifier: License :: OSI Approved :: MIT License
Classifier: Programming Language :: Python
Classifier: Programming Language :: Python :: 3
Classifier: Programming Language :: Python :: 3.6
Requires-Dist: click (==6.7)
Requires-Dist: pytest (==3.6.1)
Requires-Dist: pytest-cov (==2.5.1)
Requires-Dist: numpy (==1.14.5)
Requires-Dist: scipy (==1.1.0)
Requires-Dist: matplotlib (==2.2.2)
